fedoidcendpoint
fedoidcendpoint/oidc
