Metadata-Version: 1.1
Name: fedoidcendpoint
Version: 0.2.2
Summary: Python implementation of Federation aware OpenID Connect OP
Home-page: https://github.com/IdentityPython/fedoidcendpoint
Author: Roland Hedberg
Author-email: roland@catalogix.se
License: Apache 2.0
Platform: UNKNOWN
Classifier: Development Status :: 4 - Beta
Classifier: License :: OSI Approved :: Apache Software License
Classifier: Programming Language :: Python :: 3.4
Classifier: Programming Language :: Python :: 3.5
Classifier: Programming Language :: Python :: 3.6
Classifier: Topic :: Software Development :: Libraries :: Python Modules
